qjson2json.cp37-win32.pyd
qjson2json-0.0.5.dist-info/LICENSE.txt
qjson2json-0.0.5.dist-info/METADATA
qjson2json-0.0.5.dist-info/WHEEL
qjson2json-0.0.5.dist-info/top_level.txt
qjson2json-0.0.5.dist-info/RECORD
