Metadata-Version: 2.1
Name: qjson2json
Version: 0.0.5
Summary: Converts QJSON, a human readable JSON, into JSON
Home-page: https://github.com/qjson/qjson-py3
Maintainer: Christophe Meessen
Maintainer-email: christophe@meessen.net
License: BSD 3-Clause License
Keywords: JSON,config,QJSON
Platform: UNKNOWN
Classifier: License :: OSI Approved :: BSD License
Classifier: Programming Language :: Python :: 3
Classifier: Operating System :: OS Independent
Classifier: Topic :: Utilities
